pymupdf4llm_mcp/__init__.py
pymupdf4llm_mcp/app.py
pymupdf4llm_mcp/cli.py
pymupdf4llm_mcp-0.0.4.dist-info/METADATA
pymupdf4llm_mcp-0.0.4.dist-info/WHEEL
pymupdf4llm_mcp-0.0.4.dist-info/entry_points.txt
pymupdf4llm_mcp-0.0.4.dist-info/licenses/LICENSE
pymupdf4llm_mcp-0.0.4.dist-info/RECORD
