Metadata-Version: 2.4
Name: pymupdf4llm-mcp
Version: 0.0.4
Summary: MCP Server for pymupdf4llm
Project-URL: Homepage, https://github.com/pymupdf/pymupdf4llm-mcp/
Project-URL: Repository, https://github.com/pymupdf/pymupdf4llm-mcp/
Project-URL: Documentation, https://pymupdf.readthedocs.io/en/latest/pymupdf4llm/
Author-email: Wh1isper <jizhongsheng957@gmail.com>
License-File: LICENSE
Keywords: python
Classifier: Intended Audience :: Developers
Classifier: Programming Language :: Python
Classifier: Programming Language :: Python :: 3
Classifier: Programming Language :: Python :: 3.10
Classifier: Programming Language :: Python :: 3.11
Classifier: Programming Language :: Python :: 3.12
Classifier: Programming Language :: Python :: 3.13
Classifier: Topic :: Software Development :: Libraries :: Python Modules
Requires-Python: <4.0,>=3.10
Requires-Dist: mcp[cli]>=1.6.0
Requires-Dist: pydantic>=2.11.3
Requires-Dist: pymupdf4llm>=0.0.21
Requires-Dist: typer>=0.15.2
